oauth2_lib/__init__.py
oauth2_lib/async_api_client.py
oauth2_lib/fastapi.py
oauth2_lib/py.typed
oauth2_lib/settings.py
oauth2_lib/strawberry.py
oauth2_lib-2.6.0.dist-info/licenses/LICENSE
oauth2_lib-2.6.0.dist-info/WHEEL
oauth2_lib-2.6.0.dist-info/METADATA
oauth2_lib-2.6.0.dist-info/RECORD
